[
    {
        "fitted_function": "vif_7_deg_1",
        "coeficients": [
            0.4003159250843599,
            0.0021495415044651494,
            4.139350853161998e-08,
            -1.0322483024822486e-10
        ],
        "mean_absolute_error": 0.21772572068290477
    },
    {
        "fitted_function": "vif_7_deg_2",
        "coeficients": [
            0.48225071094051997,
            -1.0317089888020298e-08,
            2.4376534328704947e-07,
            -3.0417566149953275e-12
        ],
        "mean_absolute_error": 0.2320354484425345
    },
    {
        "fitted_function": "vif_7_deg_3",
        "coeficients": [
            0.4829837266178091,
            6.757038091365436e-08,
            -2.379875747796445e-10,
            6.051586576091533e-15
        ],
        "mean_absolute_error": 0.23852021766591255
    },
    {
        "fitted_function": "vif_7_deg_4",
        "coeficients": [
            0.5039744860822036,
            5.900468438813565e-15,
            -4.6189918426514205e-20,
            6.287067104177263e-23
        ],
        "mean_absolute_error": 0.2453836139491314
    }
]