[
    {
        "fitted_function": "vif_6_deg_1",
        "coeficients": [
            0.463819376535855,
            0.3887346342868756,
            6.730960137581616,
            -6.066275264897576
        ],
        "mean_absolute_error": 0.2277138485894225
    },
    {
        "fitted_function": "vif_6_deg_2",
        "coeficients": [
            0.49165539108793627,
            0.6585617710721166,
            -0.3830522171046117,
            0.6183009115178951
        ],
        "mean_absolute_error": 0.242387658082391
    },
    {
        "fitted_function": "vif_6_deg_3",
        "coeficients": [
            0.49845549967262337,
            5.953848413466673,
            -7.056764465325315,
            4.223594497782529
        ],
        "mean_absolute_error": 0.24088405052822126
    }
]